azure/mgmt/azurestackhci/__init__.py
azure/mgmt/azurestackhci/_azure_stack_hci_client.py
azure/mgmt/azurestackhci/_configuration.py
azure/mgmt/azurestackhci/_patch.py
azure/mgmt/azurestackhci/_vendor.py
azure/mgmt/azurestackhci/_version.py
azure/mgmt/azurestackhci/py.typed
azure/mgmt/azurestackhci/aio/__init__.py
azure/mgmt/azurestackhci/aio/_azure_stack_hci_client.py
azure/mgmt/azurestackhci/aio/_configuration.py
azure/mgmt/azurestackhci/aio/_patch.py
azure/mgmt/azurestackhci/aio/operations/__init__.py
azure/mgmt/azurestackhci/aio/operations/_arc_settings_operations.py
azure/mgmt/azurestackhci/aio/operations/_clusters_operations.py
azure/mgmt/azurestackhci/aio/operations/_extensions_operations.py
azure/mgmt/azurestackhci/aio/operations/_operations.py
azure/mgmt/azurestackhci/models/__init__.py
azure/mgmt/azurestackhci/models/_azure_stack_hci_client_enums.py
azure/mgmt/azurestackhci/models/_models_py3.py
azure/mgmt/azurestackhci/operations/__init__.py
azure/mgmt/azurestackhci/operations/_arc_settings_operations.py
azure/mgmt/azurestackhci/operations/_clusters_operations.py
azure/mgmt/azurestackhci/operations/_extensions_operations.py
azure/mgmt/azurestackhci/operations/_operations.py
azure_mgmt_azurestackhci-7.0.0.dist-info/LICENSE
azure_mgmt_azurestackhci-7.0.0.dist-info/METADATA
azure_mgmt_azurestackhci-7.0.0.dist-info/WHEEL
azure_mgmt_azurestackhci-7.0.0.dist-info/top_level.txt
azure_mgmt_azurestackhci-7.0.0.dist-info/RECORD
